[{"test":{"eth0":{"RX":{"packets":"330","bytes":"23552"},"TX":{"packets":"321","bytes":"16866"}},"lo":{"RX":{"packets":"0","bytes":"0"},"TX":{"packets":"0","bytes":"0"}}}},{"c1":{"eth0":{"RX":{"packets":"331","bytes":"23626"},"TX":{"packets":"322","bytes":"16920"}},"lo":{"RX":{"packets":"0","bytes":"0"},"TX":{"packets":"0","bytes":"0"}}}},{"c2":{"eth0":{"RX":{"packets":"331","bytes":"23626"},"TX":{"packets":"322","bytes":"16920"}},"lo":{"RX":{"packets":"0","bytes":"0"},"TX":{"packets":"0","bytes":"0"}}}},{"c3":{"eth0":{"RX":{"packets":"331","bytes":"23626"},"TX":{"packets":"322","bytes":"16920"}},"lo":{"RX":{"packets":"0","bytes":"0"},"TX":{"packets":"0","bytes":"0"}}}},{"c4":{"eth0":{"RX":{"packets":"331","bytes":"23626"},"TX":{"packets":"322","bytes":"16920"}},"lo":{"RX":{"packets":"0","bytes":"0"},"TX":{"packets":"0","bytes":"0"}}}}]