[{"kkms":{"enp0s25":{"RX":{"packets":"35690991","bytes":"16381185226"},"TX":{"packets":"50160871","bytes":"47716063583"}},"lo":{"RX":{"packets":"44170859","bytes":"335319656694"},"TX":{"packets":"44170859","bytes":"335319656694"}}}},{"peter":{"enp0s25":{"RX":{"packets":"35690916","bytes":"16381180608"},"TX":{"packets":"50160241","bytes":"47716021449"}},"lo":{"RX":{"packets":"44170656","bytes":"335319654448"},"TX":{"packets":"44170656","bytes":"335319654448"}}}},{"lauren":{"enp0s25":{"RX":{"packets":"35690739","bytes":"16381170944"},"TX":{"packets":"50160734","bytes":"47716051380"}},"lo":{"RX":{"packets":"44170805","bytes":"335319676475"},"TX":{"packets":"44170805","bytes":"335319676475"}}}},{"JUH":{"enp0s25":{"RX":{"packets":"35690423","bytes":"16381138493"},"TX":{"packets":"50160916","bytes":"47716060456"}},"lo":{"RX":{"packets":"44170645","bytes":"335319656115"},"TX":{"packets":"44170645","bytes":"335319656115"}}}},{"SHJ":{"enp0s25":{"RX":{"packets":"35690293","bytes":"16381119631"},"TX":{"packets":"50160576","bytes":"47716050112"}},"lo":{"RX":{"packets":"44170920","bytes":"335319664400"},"TX":{"packets":"44170920","bytes":"335319664400"}}}}]